{
  "_doc": "D82 — Sample-side tag manifest. SINGLE SOURCE OF TRUTH for each test sample's canonical GoF tag(s). Consumed by Codebase/Frontend/playwright/tests/all-samples.spec.ts to resolve co-emit ambiguity DETERMINISTICALLY: the e2e clicks the candidate chip whose label matches a sample's known tag (in priority order) instead of arbitrarily picking the first chip. Co-emit ambiguity itself stays by design per DESIGN_DECISIONS.md D21/D38/D80 — this manifest only feeds the SAMPLE's known answer back into the TEST. 'tags' are the exact canonical labels chips/badges render (Builder, Singleton, MethodChaining, Adapter, Decorator, Proxy, Pimpl, Strategy, Factory, ...). kind=negative rows carry tags:[] by design. Add a sample -> add a row here, or the spec's drift guard fails fast.",
  "samples": [
    {
      "file": "builder/http_request_builder.cpp",
      "family": "Creational",
      "kind": "positive",
      "classHint": "HttpRequestBuilder",
      "tags": ["Builder"]
    },
    {
      "file": "factory/shape_factory.cpp",
      "family": "Creational",
      "kind": "positive",
      "classHint": "ShapeFactory",
      "tags": ["Factory"]
    },
    {
      "file": "singleton/config_registry.cpp",
      "family": "Creational",
      "kind": "positive",
      "classHint": "ConfigRegistry",
      "tags": ["Singleton"]
    },
    {
      "file": "method_chaining/query_predicate.cpp",
      "family": "Behavioural",
      "kind": "positive",
      "classHint": "QueryPredicate",
      "tags": ["MethodChaining", "Builder"],
      "note": "D63 algorithm-known-limit: matcher co-emits Builder for fluent `return *this` chains lacking a build() terminator. Either chip satisfies the contract; MethodChaining preferred."
    },
    {
      "file": "strategy/strategy_basic.cpp",
      "family": "Behavioural",
      "kind": "positive",
      "classHint": "Compressor",
      "tags": ["Strategy"]
    },
    {
      "file": "strategy/strategy_with_pimpl.cpp",
      "family": "Behavioural",
      "kind": "positive",
      "classHint": "Strategy",
      "tags": ["Strategy", "Pimpl"]
    },
    {
      "file": "adapter/payment_gateway_adapter.cpp",
      "family": "Structural",
      "kind": "positive",
      "classHint": "LegacyPaymentAdapter",
      "tags": ["Adapter"]
    },
    {
      "file": "decorator/coffee_decorator.cpp",
      "family": "Structural",
      "kind": "positive",
      "classHint": "Beverage",
      "tags": ["Decorator"]
    },
    {
      "file": "wrapping/logging_proxy.cpp",
      "family": "Structural",
      "kind": "positive",
      "classHint": "LoggingDataService",
      "tags": ["Decorator", "Adapter", "Proxy"],
      "note": "D81 co-emit: the wrapper implements a shared interface and forwards to a same-interface member, so Adapter + Decorator co-emit (Proxy intentionally absent). Any wrapping-family chip satisfies the contract."
    },
    {
      "file": "pimpl/pimpl_basic.cpp",
      "family": "Idioms",
      "kind": "positive",
      "classHint": "Widget",
      "tags": ["Pimpl"]
    },
    {
      "file": "mixed/mixed_classes.cpp",
      "family": "Idioms",
      "kind": "positive",
      "classHint": "Logger",
      "tags": ["Singleton"],
      "note": "D81 per-class isolation: only Logger (Singleton) tags; the sibling Calculator is a plain class by design."
    },
    {
      "file": "usages/usages_basic.cpp",
      "family": "Idioms",
      "kind": "negative",
      "tags": []
    },
    {
      "file": "negative/plain_class_no_pattern.cpp",
      "family": "Regression",
      "kind": "negative",
      "tags": []
    },
    {
      "file": "negative/plain_widget.cpp",
      "family": "Regression",
      "kind": "negative",
      "tags": []
    },
    {
      "file": "usages/usages_adapter_trace.cpp",
      "family": "Idioms",
      "kind": "negative",
      "tags": []
    },
    {
      "file": "usages/usages_smart_pointers.cpp",
      "family": "Idioms",
      "kind": "negative",
      "tags": []
    }
  ]
}
